DALLE/__init__.py
DALLE/example.py
python_dalle-1.1.0.dist-info/METADATA
python_dalle-1.1.0.dist-info/WHEEL
python_dalle-1.1.0.dist-info/licenses/LICENSE
python_dalle-1.1.0.dist-info/RECORD
