Metadata-Version: 2.1
Name: Python-DALLE
Version: 1.1.0
Summary: Python library for interacting with OpenAI's Dall-E 2 AI
Project-URL: Homepage, https://github.com/HypedDomi/Python-DALLE
Project-URL: Bug Tracker, https://github.com/HypedDomi/Python-DALLE/issues
Author-email: HypedDomi <domi@bambus.me>
License: MIT License
License-File: LICENSE
Classifier: License :: OSI Approved :: MIT License
Classifier: Operating System :: OS Independent
Classifier: Programming Language :: Python :: 3
Requires-Python: >=3.7
Requires-Dist: requests~=2.28.1
